lucyfer/__init__.py
lucyfer/settings.py
lucyfer/utils.py
lucyfer/backend/__init__.py
lucyfer/backend/base.py
lucyfer/backend/django.py
lucyfer/backend/elastic.py
lucyfer/parser/__init__.py
lucyfer/parser/base.py
lucyfer/parser/django.py
lucyfer/parser/elastic.py
lucyfer/searchset/__init__.py
lucyfer/searchset/base.py
lucyfer/searchset/django.py
lucyfer/searchset/elastic.py
lucyfer/searchset/storage.py
lucyfer/searchset/utils.py
lucyfer/searchset/fields/__init__.py
lucyfer/searchset/fields/base.py
lucyfer/searchset/fields/django.py
lucyfer/searchset/fields/elastic.py
lucyfer/searchset/fields/mapping/__init__.py
lucyfer/searchset/fields/mapping/base.py
lucyfer/searchset/fields/mapping/django.py
lucyfer/searchset/fields/mapping/elastic.py
lucyfer/searchset/fields/mapping/utils.py
lucyfer-0.7.0.dist-info/LICENSE
lucyfer-0.7.0.dist-info/METADATA
lucyfer-0.7.0.dist-info/WHEEL
lucyfer-0.7.0.dist-info/top_level.txt
lucyfer-0.7.0.dist-info/RECORD
