Metadata-Version: 2.1
Name: lucyfer
Version: 0.7.0
Summary: Lucene search for DRF and elasticsearch-dsl
Home-page: https://github.com/ncopiy/django_lucy
Author: N Copiy
Author-email: ncopiy@ya.ru
License: UNKNOWN
Platform: UNKNOWN
Classifier: Programming Language :: Python :: 3
Classifier: License :: OSI Approved :: MIT License
Requires-Dist: lucyparser (>=0.1.7)
Requires-Dist: Django (>=2.0)
Requires-Dist: djangorestframework (>=3.10.0)
Provides-Extra: full
Requires-Dist: elasticsearch-dsl (~=6.4.0) ; extra == 'full'
